{
  "hash": "e43a37dd",
  "configHash": "bc2a2544",
  "lockfileHash": "69620179",
  "browserHash": "fad18083",
  "optimized": {
    "react": {
      "src": "../../node_modules/react/index.js",
      "file": "react.js",
      "fileHash": "4246a4dd",
      "needsInterop": true
    },
    "react-dom/client": {
      "src": "../../node_modules/react-dom/client.js",
      "file": "react-dom_client.js",
      "fileHash": "ac77d38c",
      "needsInterop": true
    },
    "react-router-dom": {
      "src": "../../node_modules/react-router-dom/dist/index.js",
      "file": "react-router-dom.js",
      "fileHash": "cd5865f0",
      "needsInterop": false
    }
  },
  "chunks": {
    "chunk-UWZXFKA6": {
      "file": "chunk-UWZXFKA6.js"
    },
    "chunk-UPDK7Z2H": {
      "file": "chunk-UPDK7Z2H.js"
    }
  }
}